<?xml version="1.0" encoding="UTF-8"?>
<!--<!DOCTYPE xmluiml SYSTEM "Shortcut.dtd">-->
<xmluiml xmlns="http://www.series60.com/xml/xmluiml/1" version="1.0">
  <widget id="shortcutPlugin2">

    <contentsource name="Shortcut" value="0x102750FA"/>
  
    <!-- Always visible shortcuts -->
    <!-- NOTE: these indexes start from 1 -->
    <!-- Shortcut #7, Music player -->
    <property class="Settings/Shortcut" name="0x00000007" value="localapp:0x102072C3"/>
    <!-- Shortcut #8, Radio -->
    <property class="Settings/Shortcut" name="0x00000008" value="localapp:0x10207A89"/>
    <!-- Shortcut #9, Notepad -->
    <property class="Settings/Shortcut" name="0x00000009" value="localapp:0x10005907"/>
    <!-- Shortcut #10, Video & TV -->
    <property class="Settings/Shortcut" name="0x0000000A" value="localapp:0x102750E2"/>
    <!-- Shortcut #11, Calculator -->
    <property class="Settings/Shortcut" name="0x0000000B" value="localapp:0x10005902"/>
    <!-- Shortcut #12, Bluetooth -->
    <property class="Settings/Shortcut" name="0x0000000C" value="localapp:0x10005951"/>
          
    <!-- #1 -->
    <button id="shortcutButton7" class="shortcutButton" focusable="true" _s60-initial-focus="1">
        <actions>
            <action>
                <trigger name="stylus">
                    <property name="eventtype" value="downup" />
                </trigger>
                <trigger name="activate"/>
                <trigger name="keyevent">
                    <!-- EStdKeyEnter (enum from e32keys.h) -->
                    <property name="scancode" value="3"/>
                    <property name="eventtype" value="1"/>
                </trigger>
                <event name="Shortcut/LaunchByIndex(0x00000007)"/>
            </action>  
        </actions>
        <image id="Shortcut_shortcutIcon7" class="shortcutIcon" >
            <property class="Shortcut/ShortcutIcon" name="ordinal" value="0x00000007"/>
        </image>
        <tooltip id="shortcutTooltip7" class="shortcutTooltip" >
            <text id="Shortcut_shortcutTooltipText7" class="shortcutTooltipText" >
                <property class="Shortcut/ShortcutCaption" name="ordinal" value="0x00000007"/>
            </text>
        </tooltip>
        <tooltip id="shortcutTooltip7Xsp" class="shortcutTooltipXsp" >
            <property class="policy/ContentChanged" name="shortcutButton7" value="ShowTooltips"/>

            <text id="PopupText7_caption" class="shortcutTextCaptionXsp" >
                <property class="Shortcut/ShortcutPopupCaptionLine" name="ordinal" value="0x00000007"/>
            </text>                
            <text id="PopupText7_a" class="shortcutTextXsp" >
                <property class="Shortcut/ShortcutPopup1stLine" name="ordinal" value="0x00000007"/>
                <!-- show xsp tip and hide normal tip -->
                <property class="policy/Content" name="shortcutTooltip7Xsp" value="display: block;"/>       
                <property class="policy/Content" name="shortcutTooltip7" value="display: none;"/>

                <property class="policy/emptyContent" name="shortcutTooltip7Xsp" value="display: none;"/> 
                <property class="policy/emptyContent" name="shortcutTooltip7" value="display: block;"/>
            </text>
            <text id="PopupText7_b" class="shortcutTextXsp" >
                <property class="Shortcut/ShortcutPopup2ndLine" name="ordinal" value="0x00000007"/>
                <property class="policy/emptyContent" name="PopupText7_b" value="display:none;"/> 
                <property class="policy/Content" name="PopupText7_b" value="display:block;"/>
            </text>
            <text id="PopupText7_c" class="shortcutTextXsp" >
                <property class="Shortcut/ShortcutPopup3rdLine" name="ordinal" value="0x00000007"/>
                <property class="policy/emptyContent" name="PopupText7_c" value="display:none;"/> 
                <property class="policy/Content" name="PopupText7_c" value="display:block;"/>
            </text>
        </tooltip>
    </button>
    <!-- #2 -->
    <button id="shortcutButton8" class="shortcutButton" focusable="true">
        <actions>
            <action>
                <trigger name="stylus">
                    <property name="eventtype" value="downup" />
                </trigger>
                <trigger name="activate"/>
                <trigger name="keyevent">
                    <!-- EStdKeyEnter (enum from e32keys.h) -->
                    <property name="scancode" value="3"/>                       
                    <property name="eventtype" value="1"/>                      
                </trigger>
                <event name="Shortcut/LaunchByIndex(0x00000008)"/>
            </action>               
        </actions>
        <image id="Shortcut_shortcutIcon8" class="shortcutIcon" >
            <property class="Shortcut/ShortcutIcon" name="ordinal" value="0x00000008"/>
        </image>
        <tooltip id="shortcutTooltip8" class="shortcutTooltip" >
            <text id="Shortcut_shortcutTooltipText8" class="shortcutTooltipText" >
                <property class="Shortcut/ShortcutCaption" name="ordinal" value="0x00000008"/>
            </text>             
        </tooltip>
        <tooltip id="shortcutTooltip8Xsp" class="shortcutTooltipXsp" >
            <property class="policy/ContentChanged" name="shortcutButton8" value="ShowTooltips"/>

            <text id="PopupText8_caption" class="shortcutTextCaptionXsp" >
                <property class="Shortcut/ShortcutPopupCaptionLine" name="ordinal" value="0x00000008"/>
            </text>                
            <text id="PopupText8_a" class="shortcutTextXsp" >
                <property class="Shortcut/ShortcutPopup1stLine" name="ordinal" value="0x00000008"/>
                <!-- show xsp tip and hide normal tip -->
                <property class="policy/Content" name="shortcutTooltip8Xsp" value="display: block;"/>       
                <property class="policy/Content" name="shortcutTooltip8" value="display: none;"/>

                <property class="policy/emptyContent" name="shortcutTooltip8Xsp" value="display: none;"/> 
                <property class="policy/emptyContent" name="shortcutTooltip8" value="display: block;"/>
            </text>
            <text id="PopupText8_b" class="shortcutTextXsp" >
                <property class="Shortcut/ShortcutPopup2ndLine" name="ordinal" value="0x00000008"/>
                <property class="policy/emptyContent" name="PopupText8_b" value="display:none;"/> 
                <property class="policy/Content" name="PopupText8_b" value="display:block;"/>
            </text>
            <text id="PopupText8_c" class="shortcutTextXsp" >
                <property class="Shortcut/ShortcutPopup3rdLine" name="ordinal" value="0x00000008"/>
                <property class="policy/emptyContent" name="PopupText8_c" value="display:none;"/> 
                <property class="policy/Content" name="PopupText8_c" value="display:block;"/>
            </text>
        </tooltip>          
    </button>
    <!-- #3 -->
    <button id="shortcutButton9" class="shortcutButton" focusable="true">
        <actions>
            <action>
                <trigger name="stylus">
                    <property name="eventtype" value="downup" />
                </trigger>
                <trigger name="activate"/>
                <trigger name="keyevent">
                    <!-- EStdKeyEnter (enum from e32keys.h) -->
                    <property name="scancode" value="3"/>               
                    <property name="eventtype" value="1"/>                              
                </trigger>
                <event name="Shortcut/LaunchByIndex(0x00000009)"/>
            </action>               
        </actions>
        <image id="Shortcut_shortcutIcon9" class="shortcutIcon" >
            <property class="Shortcut/ShortcutIcon" name="ordinal" value="0x00000009"/>
        </image>
        <tooltip id="shortcutTooltip9" class="shortcutTooltip" >
            <text id="Shortcut_shortcutTooltipText9" class="shortcutTooltipText" >
                <property class="Shortcut/ShortcutCaption" name="ordinal" value="0x00000009"/>
            </text>
        </tooltip>
        <tooltip id="shortcutTooltip9Xsp" class="shortcutTooltipXsp" >
            <property class="policy/ContentChanged" name="shortcutButton9" value="ShowTooltips"/>

            <text id="PopupText9_caption" class="shortcutTextCaptionXsp" >
                <property class="Shortcut/ShortcutPopupCaptionLine" name="ordinal" value="0x00000009"/>
            </text>                
            <text id="PopupText9_a" class="shortcutTextXsp" >
                <property class="Shortcut/ShortcutPopup1stLine" name="ordinal" value="0x00000009"/>
                <!-- show xsp tip and hide normal tip -->
                <property class="policy/Content" name="shortcutTooltip9Xsp" value="display: block;"/>       
                <property class="policy/Content" name="shortcutTooltip9" value="display: none;"/>

                <property class="policy/emptyContent" name="shortcutTooltip9Xsp" value="display: none;"/> 
                <property class="policy/emptyContent" name="shortcutTooltip9" value="display: block;"/>
            </text>
            <text id="PopupText9_b" class="shortcutTextXsp" >
                <property class="Shortcut/ShortcutPopup2ndLine" name="ordinal" value="0x00000009"/>
                <property class="policy/emptyContent" name="PopupText9_b" value="display:none;"/> 
                <property class="policy/Content" name="PopupText9_b" value="display:block;"/>
            </text>
            <text id="PopupText9_c" class="shortcutTextXsp" >
                <property class="Shortcut/ShortcutPopup3rdLine" name="ordinal" value="0x00000009"/>
                <property class="policy/emptyContent" name="PopupText9_c" value="display:none;"/> 
                <property class="policy/Content" name="PopupText9_c" value="display:block;"/>
            </text>
        </tooltip>          
    </button>
    <!-- #4 -->
    <button id="shortcutButton10" class="shortcutButton" focusable="true">
        <actions>
            <action>
                <trigger name="stylus">
                    <property name="eventtype" value="downup" />
                </trigger>
                <trigger name="activate"/>
                <trigger name="keyevent">
                    <!-- EStdKeyEnter (enum from e32keys.h) -->
                    <property name="scancode" value="3"/>                       
                    <property name="eventtype" value="1"/>                      
                </trigger>
                <event name="Shortcut/LaunchByIndex(0x0000000A)"/>                          
            </action>               
        </actions>
        <image id="Shortcut_shortcutIcon10" class="shortcutIcon" >
            <property class="Shortcut/ShortcutIcon" name="ordinal" value="0x0000000A"/>
        </image>
        <tooltip id="shortcutTooltip10" class="shortcutTooltip" >
            <text id="Shortcut_shortcutTooltipText10" class="shortcutTooltipText" >
                <property class="Shortcut/ShortcutCaption" name="ordinal" value="0x0000000A"/>
            </text>
        </tooltip>
        <tooltip id="shortcutTooltip10Xsp" class="shortcutTooltipXsp" >
            <property class="policy/ContentChanged" name="shortcutButton10" value="ShowTooltips"/>

            <text id="PopupText10_caption" class="shortcutTextCaptionXsp" >
                <property class="Shortcut/ShortcutPopupCaptionLine" name="ordinal" value="0x0000000A"/>
            </text>                
            <text id="PopupText10_a" class="shortcutTextXsp" >
                <property class="Shortcut/ShortcutPopup1stLine" name="ordinal" value="0x0000000A"/>
                <!-- show xsp tip and hide normal tip -->
                <property class="policy/Content" name="shortcutTooltip10Xsp" value="display: block;"/>      
                <property class="policy/Content" name="shortcutTooltip10" value="display: none;"/>

                <property class="policy/emptyContent" name="shortcutTooltip10Xsp" value="display: none;"/> 
                <property class="policy/emptyContent" name="shortcutTooltip10" value="display: block;"/>
            </text>
            <text id="PopupText10_b" class="shortcutTextXsp" >
                <property class="Shortcut/ShortcutPopup2ndLine" name="ordinal" value="0x0000000A"/>
                <property class="policy/emptyContent" name="PopupText10_b" value="display:none;"/> 
                <property class="policy/Content" name="PopupText10_b" value="display:block;"/>
            </text>
            <text id="PopupText10_c" class="shortcutTextXsp" >
                <property class="Shortcut/ShortcutPopup3rdLine" name="ordinal" value="0x0000000A"/>
                <property class="policy/emptyContent" name="PopupText10_c" value="display:none;"/> 
                <property class="policy/Content" name="PopupText10_c" value="display:block;"/>
            </text>
        </tooltip>  
    </button>
    <!-- #5 -->
    <button id="shortcutButton11" class="shortcutButton" focusable="true">
        <actions>
            <action>
                <trigger name="stylus">
                    <property name="eventtype" value="downup" />
                </trigger>
                <trigger name="activate"/>
                <trigger name="keyevent">
                    <!-- EStdKeyEnter (enum from e32keys.h) -->
                    <property name="scancode" value="3"/>
                    <property name="eventtype" value="1"/>
                </trigger>
                <event name="Shortcut/LaunchByIndex(0x0000000B)"/>
            </action>               
        </actions>
        <image id="Shortcut_shortcutIcon11" class="shortcutIcon" >
            <property class="Shortcut/ShortcutIcon" name="ordinal" value="0x0000000B"/>
        </image>
        <tooltip id="shortcutTooltip11" class="shortcutTooltip" >
            <text id="Shortcut_shortcutTooltipText11" class="shortcutTooltipText" >
                <property class="Shortcut/ShortcutCaption" name="ordinal" value="0x0000000B"/>
            </text>
        </tooltip>
        <tooltip id="shortcutTooltip11Xsp" class="shortcutTooltipXsp" >
            <property class="policy/ContentChanged" name="shortcutButton11" value="ShowTooltips"/>

            <text id="PopupText11_caption" class="shortcutTextCaptionXsp" >
                <property class="Shortcut/ShortcutPopupCaptionLine" name="ordinal" value="0x0000000B"/>
            </text>                
            <text id="PopupText11_a" class="shortcutTextXsp" >
                <property class="Shortcut/ShortcutPopup1stLine" name="ordinal" value="0x0000000B"/>
                <!-- show xsp tip and hide normal tip -->
                <property class="policy/Content" name="shortcutTooltip11Xsp" value="display: block;"/>      
                <property class="policy/Content" name="shortcutTooltip11" value="display: none;"/>

                <property class="policy/emptyContent" name="shortcutTooltip11Xsp" value="display: none;"/> 
                <property class="policy/emptyContent" name="shortcutTooltip11" value="display: block;"/>
            </text>
            <text id="PopupText11_b" class="shortcutTextXsp" >
                <property class="Shortcut/ShortcutPopup2ndLine" name="ordinal" value="0x0000000B"/>
                <property class="policy/emptyContent" name="PopupText11_b" value="display:none;"/> 
                <property class="policy/Content" name="PopupText11_b" value="display:block;"/>
            </text>
            <text id="PopupText11_c" class="shortcutTextXsp" >
                <property class="Shortcut/ShortcutPopup3rdLine" name="ordinal" value="0x0000000B"/>
                <property class="policy/emptyContent" name="PopupText11_c" value="display:none;"/> 
                <property class="policy/Content" name="PopupText11_c" value="display:block;"/>
            </text>
        </tooltip>          
    </button>
    <!-- #6 -->
    <button id="shortcutButton12" class="shortcutButton" focusable="true">
        <actions>
            <action>
                <trigger name="stylus">
                    <property name="eventtype" value="downup" />
                </trigger>
                <trigger name="activate"/>
                <trigger name="keyevent">
                    <!-- EStdKeyEnter (enum from e32keys.h) -->             
                    <property name="scancode" value="3"/> 
                    <property name="eventtype" value="1"/>
                </trigger>
                <event name="Shortcut/LaunchByIndex(0x0000000C)"/>
            </action>               
        </actions>
        <image id="Shortcut_shortcutIcon12" class="shortcutIcon" >
            <property class="Shortcut/ShortcutIcon" name="ordinal" value="0x0000000C"/>
        </image>
        <tooltip id="shortcutTooltip12" class="shortcutTooltip" >
            <text id="Shortcut_shortcutTooltipText12" class="shortcutTooltipText" >
                <property class="Shortcut/ShortcutCaption" name="ordinal" value="0x0000000C"/>
            </text>
        </tooltip>
        <tooltip id="shortcutTooltip12Xsp" class="shortcutTooltipXsp" >
            <property class="policy/ContentChanged" name="shortcutButton12" value="ShowTooltips"/>

            <text id="PopupText12_caption" class="shortcutTextCaptionXsp" >
                <property class="Shortcut/ShortcutPopupCaptionLine" name="ordinal" value="0x0000000C"/>
            </text>                
            <text id="PopupText12_a" class="shortcutTextXsp" >
                <property class="Shortcut/ShortcutPopup1stLine" name="ordinal" value="0x0000000C"/>
                <!-- show xsp tip and hide normal tip -->
                <property class="policy/Content" name="shortcutTooltip12Xsp" value="display: block;"/>      
                <property class="policy/Content" name="shortcutTooltip12" value="display: none;"/>

                <property class="policy/emptyContent" name="shortcutTooltip12Xsp" value="display: none;"/> 
                <property class="policy/emptyContent" name="shortcutTooltip12" value="display: block;"/>
            </text>
            <text id="PopupText12_b" class="shortcutTextXsp" >
                <property class="Shortcut/ShortcutPopup2ndLine" name="ordinal" value="0x0000000C"/>
                <property class="policy/emptyContent" name="PopupText12_b" value="display:none;"/> 
                <property class="policy/Content" name="PopupText12_b" value="display:block;"/>
            </text>
            <text id="PopupText12_c" class="shortcutTextXsp" >
                <property class="Shortcut/ShortcutPopup3rdLine" name="ordinal" value="0x0000000C"/>
                <property class="policy/emptyContent" name="PopupText12_c" value="display:none;"/> 
                <property class="policy/Content" name="PopupText12_c" value="display:block;"/>
            </text>
        </tooltip>  
    </button>
    <menuextension>
        <softkey type="middle" target="hs_widget_msk_open"/>
        <menuitem target="hs_widget_menuitem_open">
            <actions>
                <action>
                    <trigger name="activate"/>
                    <event name="system/activateselecteditem"/>
                </action>
            </actions>
        </menuitem>
        <menuitem target="hs_widget_menuitem_settings">
            <actions>
                <action>
                    <trigger name="activate"/>
                    <event name="Shortcut/ShowSettings(0x00000007,0x00000008,0x00000009,0x0000000A,0x0000000B,0x0000000C)"/>
                </action>
            </actions>
        </menuitem>
    </menuextension>
  </widget>
</xmluiml>
